sanic_motor/__init__.py
sanic_motor-0.7.0.dist-info/METADATA
sanic_motor-0.7.0.dist-info/WHEEL
sanic_motor-0.7.0.dist-info/top_level.txt
sanic_motor-0.7.0.dist-info/RECORD
