Metadata-Version: 2.1
Name: sanic-motor
Version: 0.7.0
Summary: Simple Motor wrapper for sanic
Home-page: https://github.com/lixxu/sanic-motor
Author: Lix Xu
Author-email: xuzenglin@gmail.com
License: BSD
Platform: any
Classifier: Environment :: Web Environment
Classifier: Intended Audience :: Developers
Classifier: License :: OSI Approved :: BSD License
Classifier: Operating System :: OS Independent
Classifier: Programming Language :: Python
Classifier: Topic :: Internet :: WWW/HTTP :: Dynamic Content
Classifier: Topic :: Software Development :: Libraries :: Python Modules
Classifier: Programming Language :: Python :: 3
Requires-Python: >=3.7
Requires-Dist: motor (>=2.0)
Requires-Dist: sanic (>=21.3)
